marshmallow_jsonapi/__init__.py
marshmallow_jsonapi/exceptions.py
marshmallow_jsonapi/fields.py
marshmallow_jsonapi/flask.py
marshmallow_jsonapi/schema.py
marshmallow_jsonapi/utils.py
marshmallow_jsonapi_minfork-0.25.0.dist-info/licenses/AUTHORS.rst
marshmallow_jsonapi_minfork-0.25.0.dist-info/licenses/LICENSE
marshmallow_jsonapi_minfork-0.25.0.dist-info/METADATA
marshmallow_jsonapi_minfork-0.25.0.dist-info/WHEEL
marshmallow_jsonapi_minfork-0.25.0.dist-info/top_level.txt
marshmallow_jsonapi_minfork-0.25.0.dist-info/RECORD
