Metadata-Version: 2.4
Name: marshmallow-jsonapi-minfork
Version: 0.25.0
Summary: JSON API 1.0 (https://jsonapi.org) formatting with marshmallow
Author-email: Steven Loria <sloria1@gmail.com>
Maintainer-email: Tomislav Adamic <tomislav.adamic@gmail.com>
License-Expression: MIT
Project-URL: Source, https://github.com/tadams42/marshmallow-jsonapi
Project-URL: Funding, https://opencollective.com/marshmallow
Project-URL: Documentation, https://marshmallow-jsonapi.readthedocs.io/en/latest/
Keywords: marshmallow-jsonapi,marshmallow,marshalling,serialization,jsonapi,deserialization,validation
Platform: any
Classifier: Intended Audience :: Developers
Classifier: Programming Language :: Python :: 3
Classifier: Programming Language :: Python :: 3.9
Classifier: Programming Language :: Python :: 3.10
Classifier: Programming Language :: Python :: 3.11
Classifier: Programming Language :: Python :: 3.12
Classifier: Programming Language :: Python :: 3.13
Classifier: Programming Language :: Python :: 3 :: Only
Requires-Python: >=3.9
License-File: LICENSE
License-File: AUTHORS.rst
Requires-Dist: marshmallow<4
Requires-Dist: flask>=2.2.0
Provides-Extra: docs
Requires-Dist: sphinx==3.5.3; extra == "docs"
Requires-Dist: sphinx-rtd-theme==0.5.0; extra == "docs"
Requires-Dist: sphinx-issues>=0.2.0; extra == "docs"
Dynamic: license-file
